examAnalyzerINF219h23/__init__.py
examAnalyzerINF219h23/app.py
examAnalyzerINF219h23/classes/Constants.py
examAnalyzerINF219h23/classes/File_gen.py
examAnalyzerINF219h23/classes/__init__.py
examAnalyzerINF219h23/classes/features/Box.py
examAnalyzerINF219h23/classes/features/GradeDistribution.py
examAnalyzerINF219h23/classes/features/PBC.py
examAnalyzerINF219h23/classes/features/QuestionTable.py
examAnalyzerINF219h23/classes/features/QuestionTimeAverage.py
examAnalyzerINF219h23/classes/features/TaskDuration.py
examAnalyzerINF219h23/classes/features/__init__.py
examAnalyzerINF219h23/classes/json/Exam.py
examAnalyzerINF219h23/classes/json/Question.py
examAnalyzerINF219h23/classes/json/Result.py
examAnalyzerINF219h23/classes/json/ResultWrapper.py
examAnalyzerINF219h23/classes/json/__init__.py
examAnalyzerINF219h23/templates/CALC_PBC.png
examAnalyzerINF219h23/templates/CALC_PBC_STD.png
examAnalyzerINF219h23/templates/index.html
examAnalyzerINF219h23-1.0.10.dist-info/LICENSE
examAnalyzerINF219h23-1.0.10.dist-info/METADATA
examAnalyzerINF219h23-1.0.10.dist-info/WHEEL
examAnalyzerINF219h23-1.0.10.dist-info/top_level.txt
examAnalyzerINF219h23-1.0.10.dist-info/RECORD
