Metadata-Version: 2.1
Name: examAnalyzerINF219h23
Version: 1.0.10
Summary: Exam analyzer is a tool that extract data from Json files from Inspera, and then creates visualizations with descriptive texts
Author: Tobias Husebø, Jonas Heen Opsahl, Brage Ramberg, Prem Eide
Author-email: premeide@gmail.com
Keywords: python,education,exam analysis
Classifier: Development Status :: 1 - Planning
Classifier: Intended Audience :: Developers
Classifier: Programming Language :: Python :: 3
Classifier: Operating System :: Unix
Classifier: Operating System :: MacOS :: MacOS X
Classifier: Operating System :: Microsoft :: Windows
License-File: LICENSE
Requires-Dist: Flask
